<WARSCAPE_PROPERTIES_FILE hidden="false" id="{f537aac5-03ec-4e16-ab90-927694fd12de}" version="27" supported_warscape_properties="16">
 <NODE hidden="false" id="{e2116c54-2dad-4efa-a948-b39c29c921d1}" name="Camera">
  <VECTOR is_linked="0" hidden="false" id="{f0f7a0e0-53be-467e-83a3-0d15e4df078b}" link_id="0" unique_id="{f0f7a0e0-53be-467e-83a3-0d15e4df078b}" name="position" surface_mode="Freeform">
   <DOUBLE hidden="false" id="{861b58e2-b12c-46c5-8654-3b5be28ca53a}" animated="1" name="X" single_keyframe_only="0" default="-279.01708984375" order="0">
    <KEYFRAME time="7.233333587646484" data="156.31643676757812"/>
    <KEYFRAME time="16.19999504089355" data="157.2001190185547"/>
   </DOUBLE>
   <DOUBLE hidden="false" id="{137d746f-fdf4-4129-a40c-e2154ab4e1c7}" animated="1" name="Y" single_keyframe_only="0" default="123.5934143066406" order="1">
    <KEYFRAME time="7.233333587646484" data="47.405818939208984"/>
    <KEYFRAME time="16.19999504089355" data="47.02314758300781"/>
   </DOUBLE>
   <DOUBLE hidden="false" id="{a9657faa-9f7f-4f2c-a70d-5aad10b9f58f}" animated="1" name="Z" single_keyframe_only="0" default="-325.5861511230469" order="2">
    <KEYFRAME time="7.233333587646484" data="463.9269714355469"/>
    <KEYFRAME time="16.19999504089355" data="466.362060546875"/>
   </DOUBLE>
  </VECTOR>
  <VECTOR is_linked="0" hidden="false" id="{d618b3fc-394f-40be-aca9-dcc888800494}" link_id="0" unique_id="{d618b3fc-394f-40be-aca9-dcc888800494}" name="target" surface_mode="Freeform">
   <DOUBLE hidden="false" id="{84e3b836-5379-4a5d-afc7-ca4c2403c234}" animated="1" name="X" single_keyframe_only="0" default="-115.0805358886719" order="0">
    <KEYFRAME time="7.233333587646484" data="22.054336547851562"/>
    <KEYFRAME time="16.19999504089355" data="-20.268417358398438"/>
   </DOUBLE>
   <DOUBLE hidden="false" id="{483260ce-5d11-429b-bae3-f5e732bd85c5}" animated="1" name="Y" single_keyframe_only="0" default="23.59342193603516" order="1">
    <KEYFRAME time="7.233333587646484" data="64.81471252441406"/>
    <KEYFRAME time="16.19999504089355" data="99.25975036621094"/>
   </DOUBLE>
   <DOUBLE hidden="false" id="{c4b8409b-a691-431e-9e9c-c62474968df9}" animated="1" name="Z" single_keyframe_only="0" default="-128.9626617431641" order="2">
    <KEYFRAME time="7.233333587646484" data="702.57958984375"/>
    <KEYFRAME time="16.19999504089355" data="673.284423828125"/>
   </DOUBLE>
  </VECTOR>
  <RADIAN hidden="false" user_friendy_name="Field of View" id="{717299b1-1cdf-4ca3-8368-fcf214c7cf7a}" animated="0" name="vertical_fov" single_keyframe_only="1" default="1.134464025497437" order="6">
   <KEYFRAME time="8.5" data="0.6632250547409058"/>
  </RADIAN>
  <NODE hidden="false" id="{711df77b-c94e-44e4-ac37-2d439bf23748}" name="rotation">
   <RADIAN hidden="false" user_friendy_name="Yaw" id="{013de2c4-c899-4b68-b667-5dc2001bdd18}" animated="0" name="yaw" single_keyframe_only="1" default="0" order="3"/>
   <RADIAN hidden="false" user_friendy_name="Pitch" id="{bcd8f2ab-7342-427a-8c04-f981fcb946af}" animated="0" name="pitch" single_keyframe_only="1" default="0" order="4"/>
   <RADIAN hidden="false" user_friendy_name="Roll" id="{547eb4a8-fd9c-4716-83fc-823089d9867d}" animated="0" name="roll" single_keyframe_only="1" default="0" order="5"/>
  </NODE>
  <DOUBLE hidden="false" user_friendy_name="Near Distance" id="{5b186a40-63a8-4b88-aa98-c5c155e40ae3}" animated="0" name="near_distance" single_keyframe_only="1" default="1" order="9"/>
  <DOUBLE hidden="false" user_friendy_name="Far Distance" id="{a5db8c5e-4ef5-4fd4-8d37-8fb7c38376d9}" animated="0" name="far_distance" single_keyframe_only="1" default="13000" order="10"/>
  <NODE hidden="false" id="{8287225c-5258-4be0-a194-98ae50f85d6b}" name="DOF">
   <DOUBLE hidden="false" id="{d6aa863d-ef52-4d24-bbb6-284a658cd844}" animated="0" name="Focal Depth" single_keyframe_only="1" default="0" order="12"/>
   <DOUBLE hidden="false" id="{803e783b-b879-46cb-9ef0-8723f309d208}" animated="0" name="Focal Width" single_keyframe_only="1" default="3.402823466385289e+38" order="13"/>
   <DOUBLE hidden="false" id="{d7a1fd17-9ee8-49e7-9c6e-9d28c816b1f6}" animated="0" name="Focal Falloff Near" single_keyframe_only="1" default="1" order="14"/>
   <DOUBLE hidden="false" id="{181abc15-03f0-4d1f-adf1-ef62912f6adf}" animated="0" name="Focal Falloff Far" single_keyframe_only="1" default="1" order="15"/>
   <DOUBLE hidden="false" user_friendy_name="Background Blur Radius" id="{5c8e06bd-4891-49ab-a714-2e349547d2fc}" animated="0" name="Blur Kernel Radius - Background" single_keyframe_only="1" default="10" order="16"/>
   <DOUBLE hidden="false" user_friendy_name="Foreground Blur Radius" id="{e03e7a93-2821-4227-a62f-c102281cd8a0}" animated="0" name="Blur Kernel Radius - Foreground" single_keyframe_only="1" default="10" order="17"/>
   <DOUBLE hidden="false" user_friendy_name="Foreground CoC Blur Radius" id="{af846976-3396-4c2d-8499-1c390f77c692}" animated="0" name="Blur Kernel Radius - Foreground CoC" single_keyframe_only="1" default="20" order="18"/>
   <DOUBLE hidden="false" id="{094b5464-0e60-4b46-9985-f0e4cd6fcadd}" animated="0" name="Bokeh Sprite Radius" single_keyframe_only="1" default="10" order="19"/>
   <DOUBLE hidden="false" id="{59495731-3067-43ce-b255-82a7a4315ddc}" animated="0" name="Bokeh Threshold" single_keyframe_only="1" default="100" order="20"/>
   <DOUBLE hidden="false" id="{bac171fe-21aa-48a0-a05d-61aec473755e}" animated="0" name="Bokeh Hotspot Kernel Size" single_keyframe_only="1" default="5" order="21"/>
   <DOUBLE hidden="false" id="{4ff844cd-de83-4c59-b321-2c5ce955787c}" animated="0" name="Bokeh Intensity" single_keyframe_only="1" default="2" order="22"/>
  </NODE>
  <NODE hidden="false" id="{c81ee469-f76a-4054-82ed-8ff2e91ffdf3}" name="time speed multipliers">
   <DOUBLE hidden="false" user_friendy_name="Global" id="{3f1daf2a-d7e2-46f9-a90a-7281f804e7a5}" animated="0" name="global" single_keyframe_only="1" default="1" order="0"/>
   <DOUBLE hidden="false" user_friendy_name="Cinematic" id="{0396901d-6b93-45c6-9f6b-77a582d9aa7e}" animated="0" name="cinematic" single_keyframe_only="1" default="1" order="1"/>
   <DOUBLE hidden="false" user_friendy_name="Game Logic" id="{2342dac5-ea9d-46ae-896d-0d7cde35bec6}" animated="0" name="game logic" single_keyframe_only="1" default="1" order="2"/>
  </NODE>
 </NODE>
</WARSCAPE_PROPERTIES_FILE>
